notion_oauth_handler/__init__.py
notion_oauth_handler/entrypoints.py
notion_oauth_handler/py.typed
notion_oauth_handler/core/__init__.py
notion_oauth_handler/core/consumer.py
notion_oauth_handler/core/dto.py
notion_oauth_handler/core/exc.py
notion_oauth_handler/core/oauth_handler.py
notion_oauth_handler/mock/__init__.py
notion_oauth_handler/mock/app.py
notion_oauth_handler/scripts/__init__.py
notion_oauth_handler/scripts/cli.py
notion_oauth_handler/server/__init__.py
notion_oauth_handler/server/app.py
notion_oauth_handler/server/auth_view.py
notion_oauth_handler/server/config.py
notion_oauth_handler/server/document_view.py
notion_oauth_handler/server/middleware.py
notion_oauth_handler-0.1.3.dist-info/LICENSE
notion_oauth_handler-0.1.3.dist-info/METADATA
notion_oauth_handler-0.1.3.dist-info/WHEEL
notion_oauth_handler-0.1.3.dist-info/entry_points.txt
notion_oauth_handler-0.1.3.dist-info/top_level.txt
notion_oauth_handler-0.1.3.dist-info/RECORD
